minimalistic_deploy/__init__.py
minimalistic_deploy/action.py
minimalistic_deploy/host.py
minimalistic_deploy/main.py
minimalistic_deploy/ssh_client.py
minimalistic_deploy/utils.py
minimalistic_deploy-0.0.2.data/scripts/deploy
minimalistic_deploy-0.0.2.dist-info/METADATA
minimalistic_deploy-0.0.2.dist-info/WHEEL
minimalistic_deploy-0.0.2.dist-info/top_level.txt
minimalistic_deploy-0.0.2.dist-info/RECORD
